{
  "trademarkList": [
    {
      "tmId": 1,
      "tmName": "小米"
    },
    {
      "tmId": 2,
      "tmName": "华为"
    },
    {
      "tmId": 3,
      "tmName": "苹果"
    }
  ],
  "attrsList": [
    {
      "attrId": 1,
      "attrName": "类型",
      "attrValueList": [
        "苹果手机",
        "安卓手机"
      ]
    }
  ],
  "goodsList": [
    {
      "attrs": null,
      "category1Id": null,
      "category1Name": null,
      "category2Id": null,
      "category2Name": null,
      "category3Id": null,
      "category3Name": null,
      "defaultImg": "./images/mi.jpeg",
      "id": 1,
      "price": 5399,
      "title": "小米12S Pro 骁龙8+处理器 徕卡光学镜头 2K超视感屏 120Hz高刷 120W秒充 12GB+256GB 黑色 5G手机",
      "tmId": null,
      "tmName": null
    }
  ],
  "total": 1,
  "pageSize": 1,
  "pageNo": 1,
  "totalPages": 1
}
